ugbib_werkzeug/__init__.py
ugbib_werkzeug/bibWerkzeug.py
ugbib_werkzeug/py.typed
ugbib_werkzeug-0.1.2.dist-info/METADATA
ugbib_werkzeug-0.1.2.dist-info/WHEEL
ugbib_werkzeug-0.1.2.dist-info/licenses/LICENSE
ugbib_werkzeug-0.1.2.dist-info/RECORD
