Metadata-Version: 2.3
Name: ugbib_werkzeug
Version: 0.1.2
Summary: Diverse Werkzeuge für Python Entwicklung
License: MIT License
Classifier: Programming Language :: Python :: 3
Classifier: Programming Language :: Python :: 3.10
Requires-Python: >=3.10
